mixstream/_MixStream.cpython-38-x86_64-linux-gnu.so
mixstream/__init__.py
mixstream-1.1.0.dist-info/LICENSE
mixstream-1.1.0.dist-info/METADATA
mixstream-1.1.0.dist-info/top_level.txt
mixstream-1.1.0.dist-info/RECORD
mixstream-1.1.0.dist-info/WHEEL
mixstream.libs/libvorbis-02341991.so.0.4.6
mixstream.libs/libSDL-1-8624f787.2.so.0.11.4
mixstream.libs/libSDL_mixer-1-f48054a8.2.so.0.12.0
mixstream.libs/libvorbisfile-c5d289a9.so.3.3.5
mixstream.libs/libSoundTouch-855df6d6.so.1.4.0
mixstream.libs/libogg-24eaa32b.so.0.8.0
