Metadata-Version: 2.1
Name: mixstream
Version: 1.1.0
Summary: MixStream is a C-extension to combine SoundTouch and SDL_mixer
Home-page: https://github.com/fofix/python-mixstream
Author: FoFiX team
Author-email: contact@fofix.org
License: GPLv2+
Keywords: music vorbis sdl soundtouch
Platform: UNKNOWN
Classifier: Intended Audience :: Developers
Classifier: License :: OSI Approved :: GNU General Public License v2 or later (GPLv2+)
Classifier: Programming Language :: Python
Classifier: Programming Language :: Python :: 3
Classifier: Programming Language :: Python :: 3.7
Classifier: Programming Language :: Python :: 3.8
Classifier: Programming Language :: Python :: 3.9
Classifier: Programming Language :: Python :: 3.10
Classifier: Topic :: Multimedia
Classifier: Topic :: Multimedia :: Sound/Audio
Classifier: Topic :: Software Development :: Libraries
License-File: LICENSE
